acm/__init__.py
acm/client.py
acm/command.py
acm/commons.py
acm/files.py
acm/params.py
acm/server.py
acm_sdk_python-0.4.12.dist-info/METADATA
acm_sdk_python-0.4.12.dist-info/WHEEL
acm_sdk_python-0.4.12.dist-info/top_level.txt
acm_sdk_python-0.4.12.dist-info/RECORD
