Metadata-Version: 2.1
Name: acm-sdk-python
Version: 0.4.12
Summary: Python client for ACM.
Home-page: UNKNOWN
Author: acm
Author-email: 755063194@qq.com
License: UNKNOWN
Platform: UNKNOWN
